JoyShockLibrary/__init__.py
python_jsl_NullMember-0.0.1.dist-info/LICENSE
python_jsl_NullMember-0.0.1.dist-info/METADATA
python_jsl_NullMember-0.0.1.dist-info/WHEEL
python_jsl_NullMember-0.0.1.dist-info/top_level.txt
python_jsl_NullMember-0.0.1.dist-info/RECORD
