Metadata-Version: 2.1
Name: python-jsl-NullMember
Version: 0.0.1
Summary: Python Wrapper for JoyShockLibrary using ctypes
Home-page: https://github.com/NullMember/python-jsl
Author: Malik Enes Safak
Author-email: e.maliksafak@gmail.com
License: UNKNOWN
Project-URL: Bug Tracker, https://github.com/NullMember/python-jsl/issues
Platform: UNKNOWN
Classifier: Programming Language :: Python :: 3
Classifier: License :: OSI Approved :: MIT License
Classifier: Operating System :: OS Independent
Requires-Python: >=3.6
License-File: LICENSE
